rubikai/__init__.py
rubikai/cube/__init__.py
rubikai/cube/cube.py
rubikai/solver/__init__.py
rubikai/solver/learning.py
rubikai/solver/search.py
rubikai/solver/solver.py
rubikai/solver/util.py
rubikai-0.1.2.dist-info/METADATA
rubikai-0.1.2.dist-info/WHEEL
rubikai-0.1.2.dist-info/top_level.txt
rubikai-0.1.2.dist-info/RECORD
