Metadata-Version: 2.1
Name: rubikai
Version: 0.1.2
Summary: Rubik AI
Home-page: UNKNOWN
Author: Forest Agostinelli
Author-email: agostinelli.f@hotmail.com
License: UNKNOWN
Platform: UNKNOWN
Classifier: Programming Language :: Python :: 3
Classifier: License :: OSI Approved :: MIT License
Classifier: Operating System :: OS Independent
Requires-Dist: numpy
Requires-Dist: pandas
